prt_nn/__init__.py
prt_nn/classification/__init__.py
prt_nn/common/__init__.py
prt_nn/common/utils.py
prt_nn/detection/__init__.py
prt_nn/detection/fast_rcnn.py
prt_nn/detection/interface.py
prt_nn/detection/metrics.py
prt_nn/detection/yolo.py
prt_nn-0.1.1.dist-info/licenses/LICENSE.md
prt_nn-0.1.1.dist-info/METADATA
prt_nn-0.1.1.dist-info/WHEEL
prt_nn-0.1.1.dist-info/top_level.txt
prt_nn-0.1.1.dist-info/RECORD
