Metadata-Version: 2.4
Name: prt-nn
Version: 0.1.1
Summary: Add your description here
Requires-Python: >=3.11
License-File: LICENSE.md
Requires-Dist: lightning>=2.5.5
Requires-Dist: torch>=2.8.0
Requires-Dist: torchmetrics[detection]>=1.8.2
Requires-Dist: ultralytics>=8.3.204
Dynamic: license-file
